KonectySdkPython/__init__.py
KonectySdkPython/cli/__init__.py
KonectySdkPython/cli/apply.py
KonectySdkPython/cli/backup.py
KonectySdkPython/cli/pull.py
KonectySdkPython/lib/__init__.py
KonectySdkPython/lib/client.py
KonectySdkPython/lib/file_manager.py
KonectySdkPython/lib/filters.py
KonectySdkPython/lib/model.py
KonectySdkPython/lib/settings.py
KonectySdkPython/lib/types.py
konecty_sdk_python-1.2.3.dist-info/METADATA
konecty_sdk_python-1.2.3.dist-info/WHEEL
konecty_sdk_python-1.2.3.dist-info/entry_points.txt
konecty_sdk_python-1.2.3.dist-info/RECORD
