Metadata-Version: 2.4
Name: konecty_sdk_python
Version: 1.2.3
Summary: Konecty SDK Python
Author-email: Leonardo Leal <leonardo.leal@konecty.com>, Derotino Silveira <derotino.silveira@konecty.com>
License: MIT
Keywords: api,konecty,sdk
Classifier: Development Status :: 4 - Beta
Classifier: Intended Audience :: Developers
Classifier: License :: OSI Approved :: MIT License
Classifier: Programming Language :: Python :: 3
Classifier: Programming Language :: Python :: 3.11
Classifier: Programming Language :: Python :: 3.12
Classifier: Topic :: Software Development :: Libraries :: Python Modules
Requires-Python: >=3.11
Requires-Dist: aiohttp>=3.11.11
Requires-Dist: asyncio>=3.4.3
Requires-Dist: black>=24.10.0
Requires-Dist: email-validator>=2.2.0
Requires-Dist: inquirer>=3.4.0
Requires-Dist: pydantic>=2.11.4
Requires-Dist: pymongo>=4.10.1
Requires-Dist: requests>=2.32.3
Requires-Dist: rich>=13.9.4
Requires-Dist: typing-extensions>=4.12.2
